{"@class":"Animation","id":{"uuid":"01A75F1F-2331-4A87-89CC-43932E5532E3"},"tracks":[{"@class":"Vector3BehaviorTrack","clips":[{"@class":"Vector3BehaviorClip","beginTime":0,"duration":12666,"script":"Vector3ValueBehaviorClipScript","behavior":{"@class":"Vector3PlainBehavior","times":[0,12666],"values":[0.0,2.70070743560791,-0.000003814697265625,-0.000006385147571563721,2.700699806213379,0.0]}}],"script":"Vector3BehaviorTrackScript","accessor":"PositionBlendAccessor"},{"@class":"QuaternionBehaviorTrack","clips":[{"@class":"QuaternionBehaviorClip","beginTime":0,"duration":12666,"script":"QuaternionValueBehaviorClipScript","behavior":{"@class":"QuaternionPlainBehavior","times":[0,12666],"values":[1.1175870895385743e-8,2.0816681711721686e-17,1.862645149230957e-9,1.0,-7.4505797087454088e-9,4.889443072642052e-9,1.4551910787474754e-9,1.0]}}],"script":"QuaternionBehaviorTrackScript","accessor":"RotationQBlendAccessor"},{"@class":"Vector3BehaviorTrack","clips":[{"@class":"Vector3BehaviorClip","beginTime":0,"duration":12666,"script":"Vector3ValueBehaviorClipScript","behavior":{"@class":"Vector3PlainBehavior","times":[0,12666],"values":[1.0,1.0,1.0,1.0,1.0000001192092896,1.0000001192092896]}}],"script":"Vector3BehaviorTrackScript","accessor":"ScaleBlendAccessor"}]}