{"@class":"Animation","id":{"uuid":"02937C04-0FDB-494F-9567-FD165ACCA2BC"},"tracks":[{"@class":"Vector3BehaviorTrack","clips":[{"@class":"Vector3BehaviorClip","beginTime":0,"duration":13399,"script":"Vector3ValueBehaviorClipScript","behavior":{"@class":"Vector3PlainBehavior","times":[0,13399],"values":[-1.862645149230957e-8,0.023200063034892083,-1.210719347000122e-8,8.66129994392395e-8,0.023200158029794694,-1.4901161193847657e-8]}}],"script":"Vector3BehaviorTrackScript","accessor":"PositionBlendAccessor"},{"@class":"QuaternionBehaviorTrack","clips":[{"@class":"QuaternionBehaviorClip","beginTime":0,"duration":13399,"script":"QuaternionValueBehaviorClipScript","behavior":{"@class":"QuaternionPlainBehavior","times":[0,13399],"values":[-0.0154336616396904,0.06404446065425873,0.002095173578709364,0.9978255033493042,-0.015433638356626034,0.06404446065425873,0.002095175441354513,0.9978255033493042]}}],"script":"QuaternionBehaviorTrackScript","accessor":"RotationQBlendAccessor"},{"@class":"Vector3BehaviorTrack","clips":[{"@class":"Vector3BehaviorClip","beginTime":0,"duration":13399,"script":"Vector3ValueBehaviorClipScript","behavior":{"@class":"Vector3PlainBehavior","times":[0,13399],"values":[1.0,1.0,0.9999999403953552,1.0,0.9999999403953552,0.9999999403953552]}}],"script":"Vector3BehaviorTrackScript","accessor":"ScaleBlendAccessor"}]}