{"@class":"Animation","id":{"uuid":"0EA3076E-6CE4-4B08-867A-F2954684FEEE"},"tracks":[{"@class":"BoolBehaviorTrack","clips":[{"@class":"BoolBehaviorClip","beginTime":0,"duration":9300,"script":"BoolValueBehaviorClipScript","behavior":{"@class":"BoolDiscreteBehavior","frames":[{"@class":"BoolKeyFrame","formula":{"@class":"BoolExpressionFormula","expression":"true"},"time":4000},{"@class":"BoolKeyFrame","formula":{"@class":"BoolExpressionFormula","expression":"false"},"time":9300}]}}],"script":"BoolBehaviorTrackScript","accessor":"Object3DEnabledBlendAccessor"},{"@class":"FloatBehaviorTrack","clips":[{"@class":"FloatBehaviorClip","beginTime":0,"duration":8300,"script":"FloatValueBehaviorClipScript","behavior":{"@class":"FloatBezierBehavior","frames":[{"@class":"FloatBezierKeyFrame","formula":{"@class":"FloatExpressionFormula","expression":"100"},"time":4000,"point1":{"values":[1.0,0.0]},"point2":{"values":[1.0,0.0]},"order":"constant","transition":true},{"@class":"FloatBezierKeyFrame","formula":{"@class":"FloatExpressionFormula","expression":"200"},"time":6300,"point1":{"values":[1.0,0.0]},"point2":{"values":[1.0,0.0]},"order":"constant","transition":true},{"@class":"FloatBezierKeyFrame","formula":{"@class":"FloatExpressionFormula","expression":"300"},"time":8300,"point1":{"values":[1.0,0.0]},"point2":{"values":[1.0,0.0]},"order":"constant","transition":true}]}}],"script":"FloatBehaviorTrackScript","accessor":"LightIntensityBlendAccessor"}]}