{"@class":"Animation","id":{"uuid":"18D248F8-23A1-43D1-9B6B-0888B3346E48"},"tracks":[{"@class":"Vector3BehaviorTrack","clips":[{"@class":"Vector3BehaviorClip","beginTime":0,"duration":966,"script":"Vector3ValueBehaviorClipScript","behavior":{"@class":"Vector3PlainBehavior","times":[0,966],"values":[-3.3527612686157229e-8,0.041321754455566409,-4.470348358154297e-8,7.450580596923828e-9,0.04132186248898506,-2.9802322387695315e-8]}}],"script":"Vector3BehaviorTrackScript","accessor":"PositionBlendAccessor"},{"@class":"QuaternionBehaviorTrack","clips":[{"@class":"QuaternionBehaviorClip","beginTime":0,"duration":966,"script":"QuaternionValueBehaviorClipScript","behavior":{"@class":"QuaternionPlainBehavior","times":[0,966],"values":[0.01475957129150629,-0.00008700711623532698,0.0003101064939983189,0.9998910427093506,0.014759552665054798,-0.0000870206204126589,0.00031012092949822545,0.9998910427093506]}}],"script":"QuaternionBehaviorTrackScript","accessor":"RotationQBlendAccessor"},{"@class":"Vector3BehaviorTrack","clips":[{"@class":"Vector3BehaviorClip","beginTime":0,"duration":966,"script":"Vector3ValueBehaviorClipScript","behavior":{"@class":"Vector3PlainBehavior","times":[0,966],"values":[0.9999999403953552,0.9999999403953552,1.0000001192092896,0.9999998807907105,0.9999999403953552,1.0000001192092896]}}],"script":"Vector3BehaviorTrackScript","accessor":"ScaleBlendAccessor"}]}