{"@class":"Animation","id":{"uuid":"2B20ECB3-97B1-4449-8D11-96D412327E8B"},"tracks":[{"@class":"Vector3BehaviorTrack","clips":[{"@class":"Vector3BehaviorClip","beginTime":0,"duration":599,"script":"Vector3ValueBehaviorClipScript","behavior":{"@class":"Vector3PlainBehavior","times":[0,599],"values":[-0.04437486454844475,0.0545441210269928,-0.08088243752717972,-0.04437486454844475,0.0545441210269928,-0.08088243752717972]}}],"script":"Vector3BehaviorTrackScript","accessor":"PositionBlendAccessor"},{"@class":"QuaternionBehaviorTrack","clips":[{"@class":"QuaternionBehaviorClip","beginTime":0,"duration":599,"script":"QuaternionValueBehaviorClipScript","behavior":{"@class":"QuaternionPlainBehavior","times":[0,599],"values":[0.89747154712677,-0.13373740017414094,-0.05646239593625069,-0.41649866104125979,0.89747154712677,-0.13373740017414094,-0.05646239593625069,-0.41649866104125979]}}],"script":"QuaternionBehaviorTrackScript","accessor":"RotationQBlendAccessor"},{"@class":"Vector3BehaviorTrack","clips":[{"@class":"Vector3BehaviorClip","beginTime":0,"duration":599,"script":"Vector3ValueBehaviorClipScript","behavior":{"@class":"Vector3PlainBehavior","times":[0,599],"values":[0.9999991655349731,0.9999991655349731,0.9999988079071045,0.9999991655349731,0.9999991655349731,0.9999988079071045]}}],"script":"Vector3BehaviorTrackScript","accessor":"ScaleBlendAccessor"}]}