{"@class":"Animation","id":{"uuid":"3A831614-A0C7-4267-9783-E5000A1EA99B"},"tracks":[{"@class":"BoolBehaviorTrack","clips":[{"@class":"BoolBehaviorClip","beginTime":0,"duration":4900,"script":"BoolValueBehaviorClipScript","behavior":{"@class":"BoolDiscreteBehavior","frames":[{"@class":"BoolKeyFrame","formula":{"@class":"BoolExpressionFormula","expression":"true"},"time":1700},{"@class":"BoolKeyFrame","formula":{"@class":"BoolExpressionFormula","expression":"false"},"time":4900}]}}],"script":"BoolBehaviorTrackScript","accessor":"Object3DEnabledBlendAccessor"}]}