{"@class":"Animation","id":{"uuid":"4F220F87-2F55-4FE4-AAC4-E019FC426F7C"},"tracks":[{"@class":"Vector3BehaviorTrack","clips":[{"@class":"Vector3BehaviorClip","beginTime":0,"duration":866,"script":"Vector3ValueBehaviorClipScript","behavior":{"@class":"Vector3PlainBehavior","times":[0,866],"values":[-3.0022122859954836,0.0000030994415283203127,0.005001068115234375,-3.0021982192993166,-0.00000476837158203125,0.004996299743652344]}}],"script":"Vector3BehaviorTrackScript","accessor":"PositionBlendAccessor"},{"@class":"QuaternionBehaviorTrack","clips":[{"@class":"QuaternionBehaviorClip","beginTime":0,"duration":866,"script":"QuaternionValueBehaviorClipScript","behavior":{"@class":"QuaternionPlainBehavior","times":[0,866],"values":[-0.000007522372015955625,0.0008326806710101664,-0.004519258625805378,0.9999894499778748,-0.000007540067144873319,0.0008326894021593034,-0.004519280977547169,0.9999894499778748]}}],"script":"QuaternionBehaviorTrackScript","accessor":"RotationQBlendAccessor"},{"@class":"Vector3BehaviorTrack","clips":[{"@class":"Vector3BehaviorClip","beginTime":0,"duration":866,"script":"Vector3ValueBehaviorClipScript","behavior":{"@class":"Vector3PlainBehavior","times":[0,866],"values":[1.0,1.0000001192092896,0.9999999403953552,1.0,1.0,1.0]}}],"script":"Vector3BehaviorTrackScript","accessor":"ScaleBlendAccessor"}]}