{"@class":"Animation","id":{"uuid":"5C562472-2FC3-48AE-AFBC-45A61C4DBAD7"},"tracks":[{"@class":"SoundTrack","clips":[{"@class":"SoundClip","beginTime":1100,"duration":1749,"script":"SoundClipScript","behavior":{"@class":"SoundSampleBehavior","volume":0.3031674325466156,"volumeModulation":0.0,"pitch":1.0,"pitchModulation":0.0,"soundSampleId":{"uuid":"44925C45-1AA7-43A9-A64F-F6134C0042F6"}},"color":{"values":[0.8509804010391235,0.34117648005485537,0.34117648005485537]}},{"@class":"SoundClip","beginTime":3600,"duration":1749,"script":"SoundClipScript","behavior":{"@class":"SoundSampleBehavior","volume":0.3031674325466156,"volumeModulation":0.0,"pitch":1.0,"pitchModulation":0.0,"soundSampleId":{"uuid":"44925C45-1AA7-43A9-A64F-F6134C0042F6"}},"color":{"values":[0.8509804010391235,0.34117648005485537,0.34117648005485537]}}],"script":"SoundTrackScript","accessor":"AudioSourceAccessor","volume":1.0},{"@class":"SoundTrack","clips":[{"@class":"SoundClip","beginTime":400,"duration":1749,"script":"SoundClipScript","behavior":{"@class":"SoundSampleBehavior","volume":0.3031674325466156,"volumeModulation":0.0,"pitch":1.0,"pitchModulation":0.0,"soundSampleId":{"uuid":"44925C45-1AA7-43A9-A64F-F6134C0042F6"}},"color":{"values":[0.8509804010391235,0.34117648005485537,0.34117648005485537]}},{"@class":"SoundClip","beginTime":2800,"duration":1749,"script":"SoundClipScript","behavior":{"@class":"SoundSampleBehavior","volume":0.3031674325466156,"volumeModulation":0.0,"pitch":1.0,"pitchModulation":0.0,"soundSampleId":{"uuid":"44925C45-1AA7-43A9-A64F-F6134C0042F6"}},"color":{"values":[0.8509804010391235,0.34117648005485537,0.34117648005485537]}}],"script":"SoundTrackScript","accessor":"AudioSourceAccessor","volume":1.0},{"@class":"SoundTrack","clips":[{"@class":"SoundClip","beginTime":1000,"duration":257,"script":"SoundClipScript","behavior":{"@class":"SoundSampleBehavior","volume":1.0,"volumeModulation":0.0,"pitch":1.0,"pitchModulation":0.0,"soundSampleId":{"uuid":"B8F0318E-2155-4948-887C-FF2104BFC526"}},"color":{"values":[0.8509804010391235,0.4431372582912445,0.34117648005485537]}},{"@class":"SoundClip","beginTime":200,"duration":257,"script":"SoundClipScript","behavior":{"@class":"SoundSampleBehavior","volume":1.0,"volumeModulation":0.0,"pitch":1.0,"pitchModulation":0.0,"soundSampleId":{"uuid":"B8F0318E-2155-4948-887C-FF2104BFC526"}},"color":{"values":[0.8509804010391235,0.4431372582912445,0.34117648005485537]}},{"@class":"SoundClip","beginTime":1800,"duration":257,"script":"SoundClipScript","behavior":{"@class":"SoundSampleBehavior","volume":1.0,"volumeModulation":0.0,"pitch":1.0,"pitchModulation":0.0,"soundSampleId":{"uuid":"B8F0318E-2155-4948-887C-FF2104BFC526"}},"color":{"values":[0.8509804010391235,0.4431372582912445,0.34117648005485537]}},{"@class":"SoundClip","beginTime":2700,"duration":257,"script":"SoundClipScript","behavior":{"@class":"SoundSampleBehavior","volume":1.0,"volumeModulation":0.0,"pitch":1.0,"pitchModulation":0.0,"soundSampleId":{"uuid":"B8F0318E-2155-4948-887C-FF2104BFC526"}},"color":{"values":[0.8509804010391235,0.4431372582912445,0.34117648005485537]}},{"@class":"SoundClip","beginTime":3600,"duration":257,"script":"SoundClipScript","behavior":{"@class":"SoundSampleBehavior","volume":1.0,"volumeModulation":0.0,"pitch":1.0,"pitchModulation":0.0,"soundSampleId":{"uuid":"B8F0318E-2155-4948-887C-FF2104BFC526"}},"color":{"values":[0.8509804010391235,0.4431372582912445,0.34117648005485537]}},{"@class":"SoundClip","beginTime":14400,"duration":404,"script":"SoundClipScript","behavior":{"@class":"SoundSampleBehavior","volume":1.0,"volumeModulation":0.0,"pitch":0.6375565528869629,"pitchModulation":0.0,"soundSampleId":{"uuid":"B8F0318E-2155-4948-887C-FF2104BFC526"}},"color":{"values":[0.8509804010391235,0.4431372582912445,0.34117648005485537]}},{"@class":"SoundClip","beginTime":15700,"duration":404,"script":"SoundClipScript","behavior":{"@class":"SoundSampleBehavior","volume":1.0,"volumeModulation":0.0,"pitch":0.6375565528869629,"pitchModulation":0.0,"soundSampleId":{"uuid":"B8F0318E-2155-4948-887C-FF2104BFC526"}},"color":{"values":[0.8509804010391235,0.4431372582912445,0.34117648005485537]}},{"@class":"SoundClip","beginTime":13100,"duration":257,"script":"SoundClipScript","behavior":{"@class":"SoundSampleBehavior","volume":1.0,"volumeModulation":0.0,"pitch":1.0,"pitchModulation":0.0,"soundSampleId":{"uuid":"B8F0318E-2155-4948-887C-FF2104BFC526"}},"color":{"values":[0.8509804010391235,0.4431372582912445,0.34117648005485537]}}],"script":"SoundTrackScript","accessor":"AudioSourceAccessor","volume":1.0},{"@class":"SoundTrack","clips":[{"@class":"SoundClip","beginTime":0,"duration":257,"script":"SoundClipScript","behavior":{"@class":"SoundSampleBehavior","volume":1.0,"volumeModulation":0.0,"pitch":1.0,"pitchModulation":0.0,"soundSampleId":{"uuid":"3A09632A-19AB-4E62-A773-68CBE107072E"}},"color":{"values":[0.8509804010391235,0.34117648005485537,0.34117648005485537]}},{"@class":"SoundClip","beginTime":800,"duration":257,"script":"SoundClipScript","behavior":{"@class":"SoundSampleBehavior","volume":1.0,"volumeModulation":0.0,"pitch":1.0,"pitchModulation":0.0,"soundSampleId":{"uuid":"3A09632A-19AB-4E62-A773-68CBE107072E"}},"color":{"values":[0.8509804010391235,0.34117648005485537,0.34117648005485537]}},{"@class":"SoundClip","beginTime":1600,"duration":257,"script":"SoundClipScript","behavior":{"@class":"SoundSampleBehavior","volume":1.0,"volumeModulation":0.0,"pitch":1.0,"pitchModulation":0.0,"soundSampleId":{"uuid":"3A09632A-19AB-4E62-A773-68CBE107072E"}},"color":{"values":[0.8509804010391235,0.34117648005485537,0.34117648005485537]}},{"@class":"SoundClip","beginTime":2500,"duration":257,"script":"SoundClipScript","behavior":{"@class":"SoundSampleBehavior","volume":1.0,"volumeModulation":0.0,"pitch":1.0,"pitchModulation":0.0,"soundSampleId":{"uuid":"3A09632A-19AB-4E62-A773-68CBE107072E"}},"color":{"values":[0.8509804010391235,0.34117648005485537,0.34117648005485537]}},{"@class":"SoundClip","beginTime":3400,"duration":257,"script":"SoundClipScript","behavior":{"@class":"SoundSampleBehavior","volume":1.0,"volumeModulation":0.0,"pitch":1.0,"pitchModulation":0.0,"soundSampleId":{"uuid":"3A09632A-19AB-4E62-A773-68CBE107072E"}},"color":{"values":[0.8509804010391235,0.34117648005485537,0.34117648005485537]}},{"@class":"SoundClip","beginTime":14000,"duration":257,"script":"SoundClipScript","behavior":{"@class":"SoundSampleBehavior","volume":1.0,"volumeModulation":0.0,"pitch":1.0,"pitchModulation":0.0,"soundSampleId":{"uuid":"3A09632A-19AB-4E62-A773-68CBE107072E"}},"color":{"values":[0.8509804010391235,0.34117648005485537,0.34117648005485537]}},{"@class":"SoundClip","beginTime":16300,"duration":257,"script":"SoundClipScript","behavior":{"@class":"SoundSampleBehavior","volume":1.0,"volumeModulation":0.0,"pitch":1.0,"pitchModulation":0.0,"soundSampleId":{"uuid":"3A09632A-19AB-4E62-A773-68CBE107072E"}},"color":{"values":[0.8509804010391235,0.34117648005485537,0.34117648005485537]}},{"@class":"SoundClip","beginTime":4200,"duration":257,"script":"SoundClipScript","behavior":{"@class":"SoundSampleBehavior","volume":1.0,"volumeModulation":0.0,"pitch":1.0,"pitchModulation":0.0,"soundSampleId":{"uuid":"3A09632A-19AB-4E62-A773-68CBE107072E"}},"color":{"values":[0.8509804010391235,0.34117648005485537,0.34117648005485537]}},{"@class":"SoundClip","beginTime":5400,"duration":5076,"script":"SoundClipScript","behavior":{"@class":"SoundSampleBehavior","volume":1.0,"volumeModulation":0.0,"pitch":1.0,"pitchModulation":0.0,"soundSampleId":{"uuid":"31F89163-FDB2-4A4E-9ACC-B06F8F283697"}},"color":{"values":[0.8509804010391235,0.34117648005485537,0.34117648005485537]}}],"script":"SoundTrackScript","accessor":"AudioSourceAccessor","volume":1.0}]}