{"@class":"Animation","id":{"uuid":"6A6C9A27-93E0-4D1F-BB1A-4D1196801533"},"tracks":[{"@class":"Vector3BehaviorTrack","clips":[{"@class":"Vector3BehaviorClip","beginTime":0,"duration":583,"script":"Vector3ValueBehaviorClipScript","behavior":{"@class":"Vector3PlainBehavior","times":[0,583],"values":[-3.952300176024437e-8,0.3304310441017151,2.2351741790771486e-8,4.988396540284157e-8,0.3304309844970703,8.195638656616211e-8]}}],"script":"Vector3BehaviorTrackScript","accessor":"PositionBlendAccessor"},{"@class":"QuaternionBehaviorTrack","clips":[{"@class":"QuaternionBehaviorClip","beginTime":0,"duration":583,"script":"QuaternionValueBehaviorClipScript","behavior":{"@class":"QuaternionPlainBehavior","times":[0,583],"values":[-0.04950351268053055,0.7410678863525391,0.11843178421258927,0.6590460538864136,-0.04950351268053055,0.7410678863525391,0.11843178421258927,0.6590460538864136]}}],"script":"QuaternionBehaviorTrackScript","accessor":"RotationQBlendAccessor"},{"@class":"Vector3BehaviorTrack","clips":[{"@class":"Vector3BehaviorClip","beginTime":0,"duration":583,"script":"Vector3ValueBehaviorClipScript","behavior":{"@class":"Vector3PlainBehavior","times":[0,583],"values":[0.9999998807907105,1.0000001192092896,0.9999999403953552,0.9999998807907105,1.0000001192092896,0.9999999403953552]}}],"script":"Vector3BehaviorTrackScript","accessor":"ScaleBlendAccessor"}]}