{"@class":"Animation","id":{"uuid":"6CE7AA39-95E1-491D-A02A-372587C765D7"},"tracks":[{"@class":"Vector3BehaviorTrack","clips":[{"@class":"Vector3BehaviorClip","beginTime":0,"duration":2433,"script":"Vector3ValueBehaviorClipScript","behavior":{"@class":"Vector3PlainBehavior","times":[0,2433],"values":[0.031700022518634799,0.05949981138110161,0.05740000307559967,0.03170003741979599,0.05949991196393967,0.05740000307559967]}}],"script":"Vector3BehaviorTrackScript","accessor":"PositionBlendAccessor"},{"@class":"QuaternionBehaviorTrack","clips":[{"@class":"QuaternionBehaviorClip","beginTime":0,"duration":2433,"script":"QuaternionValueBehaviorClipScript","behavior":{"@class":"QuaternionPlainBehavior","times":[0,2433],"values":[0.7070986032485962,0.0034537045285105707,0.003453693585470319,0.707098126411438,0.7070986032485962,0.0034536998718976976,0.003453703597187996,0.707098126411438]}}],"script":"QuaternionBehaviorTrackScript","accessor":"RotationQBlendAccessor"},{"@class":"Vector3BehaviorTrack","clips":[{"@class":"Vector3BehaviorClip","beginTime":0,"duration":2433,"script":"Vector3ValueBehaviorClipScript","behavior":{"@class":"Vector3PlainBehavior","times":[0,2433],"values":[1.0,1.000000238418579,1.0,1.0,1.0000001192092896,1.0]}}],"script":"Vector3BehaviorTrackScript","accessor":"ScaleBlendAccessor"}]}