{"@class":"Animation","id":{"uuid":"6D5485BA-294C-453B-9CD8-3F112EB98DE9"},"tracks":[{"@class":"Vector3BehaviorTrack","clips":[{"@class":"Vector3BehaviorClip","beginTime":0,"duration":3833,"script":"Vector3ValueBehaviorClipScript","behavior":{"@class":"Vector3PlainBehavior","times":[0,3833],"values":[-1.6763806343078614e-8,0.03270014002919197,1.4901161193847657e-8,-1.6763806343078614e-8,0.03270014002919197,1.4901161193847657e-8]}}],"script":"Vector3BehaviorTrackScript","accessor":"PositionBlendAccessor"},{"@class":"QuaternionBehaviorTrack","clips":[{"@class":"QuaternionBehaviorClip","beginTime":0,"duration":3833,"script":"QuaternionValueBehaviorClipScript","behavior":{"@class":"QuaternionPlainBehavior","times":[0,3833],"values":[-0.7590909600257874,-0.00661077257245779,0.04470177739858627,0.6494143605232239,-0.7590909600257874,-0.00661077257245779,0.04470177739858627,0.6494143605232239]}}],"script":"QuaternionBehaviorTrackScript","accessor":"RotationQBlendAccessor"},{"@class":"Vector3BehaviorTrack","clips":[{"@class":"Vector3BehaviorClip","beginTime":0,"duration":3833,"script":"Vector3ValueBehaviorClipScript","behavior":{"@class":"Vector3PlainBehavior","times":[0,3833],"values":[0.9999998211860657,0.9999998211860657,1.0,0.9999998211860657,0.9999998211860657,1.0]}}],"script":"Vector3BehaviorTrackScript","accessor":"ScaleBlendAccessor"}]}