{"@class":"Animation","id":{"uuid":"7C9A5C88-883D-45B7-B822-0B562EE63C6E"},"tracks":[{"@class":"Vector3BehaviorTrack","clips":[{"@class":"Vector3BehaviorClip","beginTime":0,"duration":299,"script":"Vector3ValueBehaviorClipScript","behavior":{"@class":"Vector3PlainBehavior","times":[0,299],"values":[0.01776021718978882,0.06653416156768799,0.003701837733387947,0.01776021718978882,0.06653422117233277,0.0037017948925495149]}}],"script":"Vector3BehaviorTrackScript","accessor":"PositionBlendAccessor"},{"@class":"QuaternionBehaviorTrack","clips":[{"@class":"QuaternionBehaviorClip","beginTime":0,"duration":299,"script":"QuaternionValueBehaviorClipScript","behavior":{"@class":"QuaternionPlainBehavior","times":[0,299],"values":[0.5139876008033752,-0.1595965325832367,-0.2215220183134079,0.8131874203681946,0.5139875411987305,-0.15959647297859193,-0.2215220332145691,0.8131874799728394]}}],"script":"QuaternionBehaviorTrackScript","accessor":"RotationQBlendAccessor"},{"@class":"Vector3BehaviorTrack","clips":[{"@class":"Vector3BehaviorClip","beginTime":0,"duration":299,"script":"Vector3ValueBehaviorClipScript","behavior":{"@class":"Vector3PlainBehavior","times":[0,299],"values":[0.9999998807907105,0.9999999403953552,0.9999999403953552,0.9999998211860657,0.9999999403953552,0.9999999403953552]}}],"script":"Vector3BehaviorTrackScript","accessor":"ScaleBlendAccessor"}]}