{"@class":"Animation","id":{"uuid":"7FE9269A-75F6-4C44-BA68-FE4AA57A28A3"},"tracks":[{"@class":"Vector3BehaviorTrack","clips":[{"@class":"Vector3BehaviorClip","beginTime":0,"duration":849,"script":"Vector3ValueBehaviorClipScript","behavior":{"@class":"Vector3PlainBehavior","times":[0,849],"values":[-2.7008354663848878e-8,0.015661804005503656,-2.852175384759903e-8,-2.7008354663848878e-8,0.015661804005503656,-2.852175384759903e-8]}}],"script":"Vector3BehaviorTrackScript","accessor":"PositionBlendAccessor"},{"@class":"QuaternionBehaviorTrack","clips":[{"@class":"QuaternionBehaviorClip","beginTime":0,"duration":849,"script":"QuaternionValueBehaviorClipScript","behavior":{"@class":"QuaternionPlainBehavior","times":[0,849],"values":[0.3700995147228241,0.01470153033733368,-0.027808094397187234,0.9284594655036926,0.3700995147228241,0.01470153033733368,-0.027808094397187234,0.9284594655036926]}}],"script":"QuaternionBehaviorTrackScript","accessor":"RotationQBlendAccessor"},{"@class":"Vector3BehaviorTrack","clips":[{"@class":"Vector3BehaviorClip","beginTime":0,"duration":849,"script":"Vector3ValueBehaviorClipScript","behavior":{"@class":"Vector3PlainBehavior","times":[0,849],"values":[1.0,0.9999999403953552,0.9999998807907105,1.0,0.9999999403953552,0.9999998807907105]}}],"script":"Vector3BehaviorTrackScript","accessor":"ScaleBlendAccessor"}]}