{"@class":"Animation","id":{"uuid":"7FF9EC7D-E1F3-42CB-AEBD-76EE2FD19F3A"},"tracks":[{"@class":"Vector3BehaviorTrack","clips":[{"@class":"Vector3BehaviorClip","beginTime":0,"duration":2500,"script":"Vector3ValueBehaviorClipScript","behavior":{"@class":"Vector3PlainBehavior","times":[0,2500],"values":[0.0,0.0,0.0,0.0,0.0,0.0]}}],"script":"Vector3BehaviorTrackScript","accessor":"PositionBlendAccessor"},{"@class":"QuaternionBehaviorTrack","clips":[{"@class":"QuaternionBehaviorClip","beginTime":0,"duration":2500,"script":"QuaternionValueBehaviorClipScript","behavior":{"@class":"QuaternionPlainBehavior","times":[0,2500],"values":[0.7071066498756409,8.429367426288081e-8,8.429368136830817e-8,0.70710688829422,0.7071066498756409,8.429367426288081e-8,8.429368136830817e-8,0.70710688829422]}}],"script":"QuaternionBehaviorTrackScript","accessor":"RotationQBlendAccessor"},{"@class":"Vector3BehaviorTrack","clips":[{"@class":"Vector3BehaviorClip","beginTime":0,"duration":2500,"script":"Vector3ValueBehaviorClipScript","behavior":{"@class":"Vector3PlainBehavior","times":[0,2500],"values":[1.0,0.9999998807907105,0.9999998807907105,1.0,0.9999998807907105,0.9999998807907105]}}],"script":"Vector3BehaviorTrackScript","accessor":"ScaleBlendAccessor"}]}