{"@class":"Animation","id":{"uuid":"8D39736E-0B02-452F-90CF-7080CC7977E5"},"tracks":[{"@class":"Vector3BehaviorTrack","clips":[{"@class":"Vector3BehaviorClip","beginTime":0,"duration":5033,"script":"Vector3ValueBehaviorClipScript","behavior":{"@class":"Vector3PlainBehavior","times":[0,5033],"values":[-0.04439998418092728,0.05450000986456871,-0.08089996874332428,-0.044400010257959369,0.05449988320469856,-0.08089998364448548]}}],"script":"Vector3BehaviorTrackScript","accessor":"PositionBlendAccessor"},{"@class":"QuaternionBehaviorTrack","clips":[{"@class":"QuaternionBehaviorClip","beginTime":0,"duration":5033,"script":"QuaternionValueBehaviorClipScript","behavior":{"@class":"QuaternionPlainBehavior","times":[0,5033],"values":[0.9805845022201538,-0.10370331257581711,-0.033516690135002139,-0.16302227973937989,0.9805845022201538,-0.10370331257581711,-0.033516690135002139,-0.16302227973937989]}}],"script":"QuaternionBehaviorTrackScript","accessor":"RotationQBlendAccessor"},{"@class":"Vector3BehaviorTrack","clips":[{"@class":"Vector3BehaviorClip","beginTime":0,"duration":5033,"script":"Vector3ValueBehaviorClipScript","behavior":{"@class":"Vector3PlainBehavior","times":[0,5033],"values":[1.0,0.9999998211860657,0.9999999403953552,1.0,0.9999997615814209,1.0]}}],"script":"Vector3BehaviorTrackScript","accessor":"ScaleBlendAccessor"}]}