{"@class":"Animation","id":{"uuid":"9F3F8D48-34F8-47CF-84BB-BE8AB272BE8F"},"tracks":[{"@class":"SoundTrack","clips":[{"@class":"SoundClip","beginTime":12900,"duration":8637,"script":"SoundClipScript","behavior":{"@class":"SoundSampleBehavior","volume":0.4977375566959381,"volumeModulation":0.0,"pitch":1.0,"pitchModulation":0.0,"soundSampleId":{"uuid":"5C675451-4F25-4858-9ACA-F525238C6AFF"}},"color":{"values":[0.8509804010391235,0.34117648005485537,0.34117648005485537]}}],"script":"SoundTrackScript","accessor":"AudioSourceAccessor","volume":1.0}]}