{"@class":"Animation","id":{"uuid":"A0273966-01BC-40EE-AA67-964A1C8BFB49"},"tracks":[{"@class":"BoolBehaviorTrack","clips":[{"@class":"BoolBehaviorClip","beginTime":0,"duration":5100,"script":"BoolValueBehaviorClipScript","behavior":{"@class":"BoolDiscreteBehavior","frames":[{"@class":"BoolKeyFrame","formula":{"@class":"BoolExpressionFormula","expression":"false"},"time":5100}]}}],"script":"BoolBehaviorTrackScript","accessor":"Object3DEnabledBlendAccessor"},{"@class":"SoundTrack","clips":[{"@class":"SoundClip","beginTime":1300,"duration":3000,"script":"SoundClipScript","behavior":{"@class":"SoundSampleBehavior","volume":1.0,"volumeModulation":0.0,"pitch":1.0,"pitchModulation":0.0,"soundSampleId":{"uuid":"7DBB860E-F535-4E06-AC2A-76746DC079AE"}},"color":{"values":[0.8509804010391235,0.34117648005485537,0.34117648005485537]}},{"@class":"SoundClip","beginTime":4100,"duration":824,"script":"SoundClipScript","behavior":{"@class":"SoundSampleBehavior","volume":1.0,"volumeModulation":0.0,"pitch":1.0,"pitchModulation":0.0,"soundSampleId":{"uuid":"951BB106-A687-4241-A0EF-0D9BAC94224D"}},"color":{"values":[0.9019607901573181,0.9019607901573181,0.13333334028720857]}}],"script":"SoundTrackScript","accessor":"AudioSourceAccessor","volume":1.0},{"@class":"SoundTrack","clips":[{"@class":"SoundClip","beginTime":1300,"duration":1440,"script":"SoundClipScript","behavior":{"@class":"SoundSampleBehavior","volume":1.0,"volumeModulation":0.0,"pitch":1.0,"pitchModulation":0.0,"soundSampleId":{"uuid":"E0A79D05-4351-4067-ADE9-ACA9ED8E14E1"}},"color":{"values":[0.8509804010391235,0.4431372582912445,0.34117648005485537]}},{"@class":"SoundClip","beginTime":2900,"duration":824,"script":"SoundClipScript","behavior":{"@class":"SoundSampleBehavior","volume":1.0,"volumeModulation":0.0,"pitch":1.0,"pitchModulation":0.0,"soundSampleId":{"uuid":"15D857B7-041D-46D7-8F1E-3F0926D75661"}},"color":{"values":[0.8509804010391235,0.5882353186607361,0.2549019753932953]}},{"@class":"SoundClip","beginTime":3800,"duration":553,"script":"SoundClipScript","behavior":{"@class":"SoundSampleBehavior","volume":1.0,"volumeModulation":0.0,"pitch":1.0,"pitchModulation":0.0,"soundSampleId":{"uuid":"D19CD1EB-AE74-4C20-8507-2D94578A903C"}},"color":{"values":[0.8509804010391235,0.7176470756530762,0.12941177189350129]}},{"@class":"SoundClip","beginTime":4400,"duration":553,"script":"SoundClipScript","behavior":{"@class":"SoundSampleBehavior","volume":1.0,"volumeModulation":0.0,"pitch":1.0,"pitchModulation":0.0,"soundSampleId":{"uuid":"A5D00CFF-93F1-42F4-8844-CC0511E9F3E7"}},"color":{"values":[0.5843137502670288,0.8705882430076599,0.04313725605607033]}}],"script":"SoundTrackScript","accessor":"AudioSourceAccessor","volume":1.0}]}