{"@class":"Animation","id":{"uuid":"AC5DBB96-A5E9-4853-A8A2-935CB01CF01C"},"tracks":[{"@class":"Vector3BehaviorTrack","clips":[{"@class":"Vector3BehaviorClip","beginTime":0,"duration":9433,"script":"Vector3ValueBehaviorClipScript","behavior":{"@class":"Vector3PlainBehavior","times":[0,9433],"values":[1.2922100722789765e-8,0.05320001766085625,2.421438694000244e-8,-3.725290298461914e-9,0.05320001393556595,4.470348358154297e-8]}}],"script":"Vector3BehaviorTrackScript","accessor":"PositionBlendAccessor"},{"@class":"QuaternionBehaviorTrack","clips":[{"@class":"QuaternionBehaviorClip","beginTime":0,"duration":9433,"script":"QuaternionValueBehaviorClipScript","behavior":{"@class":"QuaternionPlainBehavior","times":[0,9433],"values":[-0.05082858353853226,-0.0002657166332937777,-0.014493435621261597,0.9986022114753723,-0.05082857608795166,-0.00026572583010420203,-0.014493429102003575,0.9986022114753723]}}],"script":"QuaternionBehaviorTrackScript","accessor":"RotationQBlendAccessor"},{"@class":"Vector3BehaviorTrack","clips":[{"@class":"Vector3BehaviorClip","beginTime":0,"duration":9433,"script":"Vector3ValueBehaviorClipScript","behavior":{"@class":"Vector3PlainBehavior","times":[0,9433],"values":[0.9999999403953552,1.0,1.000000238418579,0.9999998211860657,0.9999999403953552,1.0000001192092896]}}],"script":"Vector3BehaviorTrackScript","accessor":"ScaleBlendAccessor"}]}