{"@class":"Animation","id":{"uuid":"BB6831DA-FFCF-4F3F-B1E6-AE9B9927154C"},"tracks":[{"@class":"Vector3BehaviorTrack","clips":[{"@class":"Vector3BehaviorClip","beginTime":0,"duration":17799,"script":"Vector3ValueBehaviorClipScript","behavior":{"@class":"Vector3PlainBehavior","times":[0,17799],"values":[-0.044399991631507876,0.05449988320469856,-0.08089993894100189,-0.044399917125701907,0.0545000359416008,-0.08089999109506607]}}],"script":"Vector3BehaviorTrackScript","accessor":"PositionBlendAccessor"},{"@class":"QuaternionBehaviorTrack","clips":[{"@class":"QuaternionBehaviorClip","beginTime":0,"duration":17799,"script":"QuaternionValueBehaviorClipScript","behavior":{"@class":"QuaternionPlainBehavior","times":[0,17799],"values":[0.9805845022201538,-0.1037033423781395,-0.03351670131087303,-0.16302219033241273,0.9805845022201538,-0.1037033200263977,-0.03351670876145363,-0.16302219033241273]}}],"script":"QuaternionBehaviorTrackScript","accessor":"RotationQBlendAccessor"},{"@class":"Vector3BehaviorTrack","clips":[{"@class":"Vector3BehaviorClip","beginTime":0,"duration":17799,"script":"Vector3ValueBehaviorClipScript","behavior":{"@class":"Vector3PlainBehavior","times":[0,17799],"values":[1.0,0.9999997019767761,1.0000001192092896,1.0,0.9999997615814209,1.0]}}],"script":"Vector3BehaviorTrackScript","accessor":"ScaleBlendAccessor"}]}