{"@class":"Animation","id":{"uuid":"C3B60E80-C10D-45FF-98EE-2F21D6A529D9"},"tracks":[{"@class":"Vector3BehaviorTrack","clips":[{"@class":"Vector3BehaviorClip","beginTime":0,"duration":6099,"script":"Vector3ValueBehaviorClipScript","behavior":{"@class":"Vector3PlainBehavior","times":[0,6099],"values":[-2.9802322387695315e-8,0.015699902549386026,3.3527612686157229e-8,1.862645149230957e-9,0.015699876472353936,-6.461050361394882e-9]}}],"script":"Vector3BehaviorTrackScript","accessor":"PositionBlendAccessor"},{"@class":"QuaternionBehaviorTrack","clips":[{"@class":"QuaternionBehaviorClip","beginTime":0,"duration":6099,"script":"QuaternionValueBehaviorClipScript","behavior":{"@class":"QuaternionPlainBehavior","times":[0,6099],"values":[-0.02299526147544384,-0.013400076888501645,0.007528871297836304,0.9996173977851868,-0.022995254024863244,-0.013400076888501645,0.007528859190642834,0.9996173977851868]}}],"script":"QuaternionBehaviorTrackScript","accessor":"RotationQBlendAccessor"},{"@class":"Vector3BehaviorTrack","clips":[{"@class":"Vector3BehaviorClip","beginTime":0,"duration":6099,"script":"Vector3ValueBehaviorClipScript","behavior":{"@class":"Vector3PlainBehavior","times":[0,6099],"values":[1.0,1.0000001192092896,0.9999999403953552,1.0,1.0000001192092896,0.9999999403953552]}}],"script":"Vector3BehaviorTrackScript","accessor":"ScaleBlendAccessor"}]}