{"@class":"Animation","id":{"uuid":"DEF45E2F-CC85-4BAC-9F9B-D26910479EE2"},"tracks":[{"@class":"Vector3BehaviorTrack","clips":[{"@class":"Vector3BehaviorClip","beginTime":0,"duration":13866,"script":"Vector3ValueBehaviorClipScript","behavior":{"@class":"Vector3PlainBehavior","times":[0,13866],"values":[0.0,0.015699997544288636,-1.3969838619232178e-8,0.0,0.01569998264312744,-7.450580596923828e-9]}}],"script":"Vector3BehaviorTrackScript","accessor":"PositionBlendAccessor"},{"@class":"QuaternionBehaviorTrack","clips":[{"@class":"QuaternionBehaviorClip","beginTime":0,"duration":13866,"script":"QuaternionValueBehaviorClipScript","behavior":{"@class":"QuaternionPlainBehavior","times":[0,13866],"values":[-0.022995250299572946,0.013400168158113957,-0.007528836838901043,0.9996173977851868,-0.022995268926024438,0.013400186784565449,-0.007528861053287983,0.9996173977851868]}}],"script":"QuaternionBehaviorTrackScript","accessor":"RotationQBlendAccessor"},{"@class":"Vector3BehaviorTrack","clips":[{"@class":"Vector3BehaviorClip","beginTime":0,"duration":13866,"script":"Vector3ValueBehaviorClipScript","behavior":{"@class":"Vector3PlainBehavior","times":[0,13866],"values":[1.0,1.0000001192092896,0.9999998807907105,1.0,1.0,0.9999998211860657]}}],"script":"Vector3BehaviorTrackScript","accessor":"ScaleBlendAccessor"}]}