{"@class":"Animation","id":{"uuid":"F1F91896-41F1-42FA-B12F-F0B4DB9F8BC4"},"tracks":[{"@class":"Vector3BehaviorTrack","clips":[{"@class":"Vector3BehaviorClip","beginTime":0,"duration":3533,"script":"Vector3ValueBehaviorClipScript","behavior":{"@class":"Vector3PlainBehavior","times":[0,3533],"values":[2.9802322387695315e-8,0.02229999750852585,1.862645149230957e-8,-1.4901161193847657e-8,0.022300031036138536,2.3283064365386964e-8]}}],"script":"Vector3BehaviorTrackScript","accessor":"PositionBlendAccessor"},{"@class":"QuaternionBehaviorTrack","clips":[{"@class":"QuaternionBehaviorClip","beginTime":0,"duration":3533,"script":"QuaternionValueBehaviorClipScript","behavior":{"@class":"QuaternionPlainBehavior","times":[0,3533],"values":[-0.007323613855987787,-0.009460927918553353,0.003847734769806266,0.9999210238456726,-0.007323599420487881,-0.009460914880037308,0.003847709624096751,0.9999210238456726]}}],"script":"QuaternionBehaviorTrackScript","accessor":"RotationQBlendAccessor"},{"@class":"Vector3BehaviorTrack","clips":[{"@class":"Vector3BehaviorClip","beginTime":0,"duration":3533,"script":"Vector3ValueBehaviorClipScript","behavior":{"@class":"Vector3PlainBehavior","times":[0,3533],"values":[1.0,0.9999999403953552,0.9999999403953552,0.9999998807907105,0.9999997615814209,0.9999998211860657]}}],"script":"Vector3BehaviorTrackScript","accessor":"ScaleBlendAccessor"}]}