{"@class":"Animation","id":{"uuid":"FB678D73-7DE1-412B-83E2-730F1740A1B7"},"tracks":[{"@class":"Vector3BehaviorTrack","clips":[{"@class":"Vector3BehaviorClip","beginTime":0,"duration":866,"script":"Vector3ValueBehaviorClipScript","behavior":{"@class":"Vector3PlainBehavior","times":[0,866],"values":[3.0021958351135256,-0.0000019073486328125,0.004993438720703125,3.0021979808807375,0.0000045299530029296879,0.005000591278076172]}}],"script":"Vector3BehaviorTrackScript","accessor":"PositionBlendAccessor"},{"@class":"QuaternionBehaviorTrack","clips":[{"@class":"QuaternionBehaviorClip","beginTime":0,"duration":866,"script":"QuaternionValueBehaviorClipScript","behavior":{"@class":"QuaternionPlainBehavior","times":[0,866],"values":[-0.0000075288912739779338,-0.0008326344541274011,0.004519316367805004,0.9999894499778748,-0.000007505258508899715,-0.0008326373645104468,0.00451931357383728,0.9999894499778748]}}],"script":"QuaternionBehaviorTrackScript","accessor":"RotationQBlendAccessor"},{"@class":"Vector3BehaviorTrack","clips":[{"@class":"Vector3BehaviorClip","beginTime":0,"duration":866,"script":"Vector3ValueBehaviorClipScript","behavior":{"@class":"Vector3PlainBehavior","times":[0,866],"values":[1.0000001192092896,1.0,0.9999999403953552,1.0,1.0,0.9999999403953552]}}],"script":"Vector3BehaviorTrackScript","accessor":"ScaleBlendAccessor"}]}