{"@class":"Animation","id":{"uuid":"FCD595CA-039B-4BFE-B7B4-7F05A838BDA8"},"tracks":[{"@class":"SoundTrack","clips":[{"@class":"SoundClip","beginTime":0,"duration":59998,"script":"SoundClipScript","behavior":{"@class":"SoundSampleBehavior","volume":1.0,"volumeModulation":0.0,"pitch":1.0,"pitchModulation":0.0,"soundSampleId":{"uuid":"D49FD2CE-1AA8-4792-9B04-AA51509E1A38"}},"color":{"values":[0.8509804010391235,0.7176470756530762,0.12941177189350129]}}],"script":"SoundTrackScript","accessor":"AudioSourceAccessor","volume":1.0},{"@class":"SoundTrack","clips":[{"@class":"SoundClip","beginTime":7100,"duration":1422,"script":"SoundClipScript","behavior":{"@class":"SoundSampleBehavior","volume":1.0,"volumeModulation":0.0,"pitch":1.0,"pitchModulation":0.0,"soundSampleId":{"uuid":"E0F0BED5-CD31-403F-B1AB-FCE3F61BF4B6"}},"color":{"values":[0.054901961237192157,0.7882353067398071,0.800000011920929]}},{"@class":"SoundClip","beginTime":26100,"duration":3779,"script":"SoundClipScript","behavior":{"@class":"SoundSampleBehavior","volume":0.20361991226673127,"volumeModulation":0.0,"pitch":1.0,"pitchModulation":0.0,"soundSampleId":{"uuid":"45B3DBB0-01DD-43A0-9426-23D2D899B4BD"}},"color":{"values":[0.8509804010391235,0.5882353186607361,0.2549019753932953]}},{"@class":"SoundClip","beginTime":22400,"duration":2887,"script":"SoundClipScript","behavior":{"@class":"SoundSampleBehavior","volume":0.39819005131721499,"volumeModulation":0.0,"pitch":1.0,"pitchModulation":0.0,"soundSampleId":{"uuid":"9377BDEC-3392-4950-B361-91A1B7664B07"}},"color":{"values":[0.8509804010391235,0.7176470756530762,0.12941177189350129]}},{"@class":"SoundClip","beginTime":32100,"duration":456,"script":"SoundClipScript","behavior":{"@class":"SoundSampleBehavior","volume":0.3031674325466156,"volumeModulation":0.0,"pitch":1.0,"pitchModulation":0.0,"soundSampleId":{"uuid":"B35B6D40-E15D-4F1A-B6E3-1DB4C0B4F372"}},"color":{"values":[0.9019607901573181,0.9019607901573181,0.13333334028720857]}},{"@class":"SoundClip","beginTime":1400,"duration":456,"script":"SoundClipScript","behavior":{"@class":"SoundSampleBehavior","volume":0.15837104618549348,"volumeModulation":0.0,"pitch":1.0,"pitchModulation":0.0,"soundSampleId":{"uuid":"B35B6D40-E15D-4F1A-B6E3-1DB4C0B4F372"}},"color":{"values":[0.9019607901573181,0.9019607901573181,0.13333334028720857]}},{"@class":"SoundClip","beginTime":40300,"duration":1412,"script":"SoundClipScript","behavior":{"@class":"SoundSampleBehavior","volume":0.39819005131721499,"volumeModulation":0.0,"pitch":1.0,"pitchModulation":0.0,"soundSampleId":{"uuid":"5880AAFB-DEA3-4681-A5B6-7F01F6D1E131"}},"color":{"values":[0.8509804010391235,0.34117648005485537,0.34117648005485537]}},{"@class":"SoundClip","beginTime":54000,"duration":1422,"script":"SoundClipScript","behavior":{"@class":"SoundSampleBehavior","volume":1.0,"volumeModulation":0.0,"pitch":1.0,"pitchModulation":0.0,"soundSampleId":{"uuid":"E0F0BED5-CD31-403F-B1AB-FCE3F61BF4B6"}},"color":{"values":[0.054901961237192157,0.7882353067398071,0.800000011920929]}},{"@class":"SoundClip","beginTime":4100,"duration":1412,"script":"SoundClipScript","behavior":{"@class":"SoundSampleBehavior","volume":0.1719457060098648,"volumeModulation":0.0,"pitch":1.0,"pitchModulation":0.0,"soundSampleId":{"uuid":"5880AAFB-DEA3-4681-A5B6-7F01F6D1E131"}},"color":{"values":[0.8509804010391235,0.34117648005485537,0.34117648005485537]}}],"script":"SoundTrackScript","accessor":"AudioSourceAccessor","volume":1.0},{"@class":"SoundTrack","clips":[{"@class":"SoundClip","beginTime":2100,"duration":2114,"script":"SoundClipScript","behavior":{"@class":"SoundSampleBehavior","volume":0.20361991226673127,"volumeModulation":0.0,"pitch":1.0,"pitchModulation":0.0,"soundSampleId":{"uuid":"24E5A3D4-619B-40F8-A8C9-8A99B1C9D497"}},"color":{"values":[0.8509804010391235,0.34117648005485537,0.34117648005485537]}},{"@class":"SoundClip","beginTime":11500,"duration":4248,"script":"SoundClipScript","behavior":{"@class":"SoundSampleBehavior","volume":0.19909502565860749,"volumeModulation":0.0,"pitch":1.0,"pitchModulation":0.0,"soundSampleId":{"uuid":"6B8D55B2-802B-43B8-98F2-C0B96988BC7B"}},"color":{"values":[0.8509804010391235,0.4431372582912445,0.34117648005485537]}},{"@class":"SoundClip","beginTime":32700,"duration":4489,"script":"SoundClipScript","behavior":{"@class":"SoundSampleBehavior","volume":1.0,"volumeModulation":0.0,"pitch":1.0,"pitchModulation":0.0,"soundSampleId":{"uuid":"3928B9B4-6ADE-4C82-90E6-3E094652D96C"}},"color":{"values":[0.5843137502670288,0.8705882430076599,0.04313725605607033]}},{"@class":"SoundClip","beginTime":58000,"duration":1412,"script":"SoundClipScript","behavior":{"@class":"SoundSampleBehavior","volume":0.40271493792533877,"volumeModulation":0.0,"pitch":1.0,"pitchModulation":0.0,"soundSampleId":{"uuid":"5880AAFB-DEA3-4681-A5B6-7F01F6D1E131"}},"color":{"values":[0.8509804010391235,0.34117648005485537,0.34117648005485537]}},{"@class":"SoundClip","beginTime":47900,"duration":2887,"script":"SoundClipScript","behavior":{"@class":"SoundSampleBehavior","volume":0.39819005131721499,"volumeModulation":0.0,"pitch":1.0,"pitchModulation":0.0,"soundSampleId":{"uuid":"9377BDEC-3392-4950-B361-91A1B7664B07"}},"color":{"values":[0.8509804010391235,0.7176470756530762,0.12941177189350129]}}],"script":"SoundTrackScript","accessor":"AudioSourceAccessor","volume":1.0}]}