{"@class":"TimeLineScript","id":{"uuid":"05583157-F23B-432A-8DC0-8A2A509FEAAF"},"name":"Animation","enableOnAwake":false,"loop":true,"jumpToFirstFrameAtEnd":false,"speed":1.0,"weight":1.0,"loopStartTime":0,"loopDuration":0,"is_imported":false,"type":"user","scripts":{"@class":"StdListRuntimeScript","list":[{"@class":"AnimationScript","id":{"uuid":"D2D31B0D-B038-404C-A49F-0C61E8AACBC9"},"name":"Cylinder.004","enableOnAwake":false,"OwnerLink":{"@class":"BindingLink","targetId":{"uuid":"94832555-FD68-44C5-8525-0258E906F663"},"targetRelativeAddress":{"@class":"NodeRelativeAddressBase","index":1,"name":"P2"}},"animation":{"uuid":"6C916206-0E9D-420D-AD6C-E1C81DEDB501"},"AnimationType":"object3D","is_imported":false,"isEnabled":true}]},"triggers":[{"@class":"AnimationTrigger","id":{"uuid":"BED85D93-8D96-4B6B-8905-A1D0977B7FE0"},"ownerScriptId":{"uuid":"05583157-F23B-432A-8DC0-8A2A509FEAAF"},"logicOperation":0,"resultType":0,"isInverted":false,"event":2,"bindingLink":{"@class":"BindingLink","targetId":{"uuid":"C666BE2D-1B72-4EDC-90E5-2D160C22CA74"}}}]}