{"@class":"TimeLineScript","id":{"uuid":"08CCCBC3-E80C-457C-833B-F5B406CA3B8A"},"name":"Animation","enableOnAwake":false,"loop":true,"jumpToFirstFrameAtEnd":false,"speed":1.0,"weight":1.0,"loopStartTime":0,"loopDuration":0,"is_imported":false,"type":"user","scripts":{"@class":"StdListRuntimeScript","list":[{"@class":"AnimationScript","id":{"uuid":"3E5A8468-6374-40D5-ACCE-B5B9893C2BD6"},"name":"Light beam","enableOnAwake":false,"OwnerLink":{"@class":"BindingLink","targetId":{"uuid":"8FE7A5F1-3E98-4DEA-B416-6F5C2F0FEA57"},"targetRelativeAddress":{"@class":"NodeRelativeAddressBase","index":1,"name":"Torch","subaddress":{"@class":"NodeRelativeAddressBase","index":0,"name":"Light beam"}}},"animation":{"uuid":"5ADF5412-32C3-49E2-9369-4DB2031B9505"},"AnimationType":"object3D","is_imported":false,"isEnabled":true}]},"triggers":[{"@class":"CollisionTrigger","id":{"uuid":"74BDC891-9C10-427E-918B-CEDEA1087AA6"},"ownerScriptId":{"uuid":"08CCCBC3-E80C-457C-833B-F5B406CA3B8A"},"logicOperation":0,"resultType":0,"isInverted":false,"eventType":"inside","targetBindingLink":{"@class":"BindingLink","targetId":{"uuid":"B2170EB5-1DCB-4BCB-B239-768061E6F0CE"}},"zoneBindingLink":{"@class":"BindingLink","targetId":{"uuid":"275777AE-D909-4853-95B5-0853F14EA559"}}},{"@class":"CollisionTrigger","id":{"uuid":"EA80B923-73AA-4243-9FD2-459E1B247045"},"ownerScriptId":{"uuid":"08CCCBC3-E80C-457C-833B-F5B406CA3B8A"},"logicOperation":0,"resultType":0,"isInverted":false,"eventType":"inside","targetBindingLink":{"@class":"BindingLink","targetId":{"uuid":"B2170EB5-1DCB-4BCB-B239-768061E6F0CE"}},"zoneBindingLink":{"@class":"BindingLink","targetId":{"uuid":"A2D1CCC0-F4E8-4C84-86D1-27D80E96F841"}}},{"@class":"GroupTrigger","id":{"uuid":"72B486B2-C20F-4AD0-B362-2E2192EBACBD"},"ownerScriptId":{"uuid":"08CCCBC3-E80C-457C-833B-F5B406CA3B8A"},"logicOperation":1,"resultType":0,"isInverted":false,"triggers":[{"@class":"CollisionTrigger","id":{"uuid":"C7571875-568C-4645-8548-742218EEEC30"},"ownerScriptId":{"uuid":"08CCCBC3-E80C-457C-833B-F5B406CA3B8A"},"logicOperation":1,"resultType":0,"isInverted":true,"eventType":"out","targetBindingLink":{"@class":"BindingLink","targetId":{"uuid":"B2170EB5-1DCB-4BCB-B239-768061E6F0CE"}},"zoneBindingLink":{"@class":"BindingLink","targetId":{"uuid":"275777AE-D909-4853-95B5-0853F14EA559"}}},{"@class":"CollisionTrigger","id":{"uuid":"215F6AF1-3118-4DF7-B939-F4AC1B9B8539"},"ownerScriptId":{"uuid":"08CCCBC3-E80C-457C-833B-F5B406CA3B8A"},"logicOperation":0,"resultType":0,"isInverted":true,"eventType":"out","targetBindingLink":{"@class":"BindingLink","targetId":{"uuid":"B2170EB5-1DCB-4BCB-B239-768061E6F0CE"}},"zoneBindingLink":{"@class":"BindingLink","targetId":{"uuid":"A2D1CCC0-F4E8-4C84-86D1-27D80E96F841"}}}]}]}