{"@class":"TimeLineScript","id":{"uuid":"55AFEDA7-188C-421F-8E08-836A49CDAF90"},"name":"Scene_01 Animation 1","enableOnAwake":false,"loop":false,"jumpToFirstFrameAtEnd":false,"speed":1.0,"weight":1.0,"loopStartTime":0,"loopDuration":0,"is_imported":false,"type":"user","scripts":{"@class":"StdListRuntimeScript","list":[{"@class":"AnimationScript","id":{"uuid":"B3ABBCBC-B9C6-4083-8B7A-A96041820116"},"name":"thc4_T-pose","enableOnAwake":false,"OwnerLink":{"@class":"BindingLink","targetId":{"uuid":"7C4F50D3-A6C5-4480-8B3F-4023F7BFF2C4"}},"animation":{"uuid":"3D3CF0B2-6424-44B2-AD47-1B826EF5E59C"},"AnimationType":"object3D","is_imported":false,"isEnabled":true}]},"triggers":[{"@class":"AnimationTrigger","id":{"uuid":"15996CD2-8432-498E-B737-8F7B45309E7C"},"ownerScriptId":{"uuid":"55AFEDA7-188C-421F-8E08-836A49CDAF90"},"logicOperation":0,"resultType":0,"isInverted":false,"event":1,"bindingLink":{"@class":"BindingLink","targetId":{"uuid":"13DA0A56-4AE2-47BA-BC38-F0B178988826"}}}]}