{"@class":"TimeLineScript","id":{"uuid":"692F3C1C-141F-4D48-B1D5-F650B0434EBC"},"name":"Animation","enableOnAwake":false,"loop":false,"jumpToFirstFrameAtEnd":false,"speed":1.0,"weight":1.0,"loopStartTime":0,"loopDuration":0,"is_imported":false,"type":"user","scripts":{"@class":"StdListRuntimeScript","list":[{"@class":"AnimationScript","id":{"uuid":"672B3F1A-74C3-4F66-BE6C-33D723196E3C"},"name":"P1","enableOnAwake":false,"OwnerLink":{"@class":"BindingLink","targetId":{"uuid":"0265363B-1617-4259-8D5C-E5710F702451"},"targetRelativeAddress":{"@class":"NodeRelativeAddressBase","index":0,"name":"particles 2","subaddress":{"@class":"NodeRelativeAddressBase","index":0,"name":"P1"}}},"animation":{"uuid":"2E6E3E86-6264-4703-A510-41F37A45E4A2"},"AnimationType":"object3D","is_imported":false,"isEnabled":true},{"@class":"AnimationScript","id":{"uuid":"7D71F7B6-DEE0-41D2-9E06-D3FD3C4951D2"},"name":"Particles","enableOnAwake":false,"OwnerLink":{"@class":"BindingLink","targetId":{"uuid":"9449471A-8A95-45D7-A0D4-DA2ACACA8576"},"targetRelativeAddress":{"@class":"NodeRelativeAddressBase","index":0,"name":"particles 2","subaddress":{"@class":"NodeRelativeAddressBase","index":0,"name":"P1","subaddress":{"@class":"NodeRelativeAddressBase","index":0,"name":"Particles"}}}},"animation":{"uuid":"A2A5C9EE-47AD-43D6-ADF8-E9B4F8E4F69F"},"AnimationType":"object3D","is_imported":false,"isEnabled":true},{"@class":"AnimationScript","id":{"uuid":"A40BCD0F-1FCB-4DC5-BEBE-73E84ADF5D64"},"name":"P2","enableOnAwake":false,"OwnerLink":{"@class":"BindingLink","targetId":{"uuid":"AF6C8A6D-DCC9-4816-B351-CE31215284A4"},"targetRelativeAddress":{"@class":"NodeRelativeAddressBase","index":0,"name":"particles 2","subaddress":{"@class":"NodeRelativeAddressBase","index":1,"name":"P2"}}},"animation":{"uuid":"1783AA2F-FD40-4177-9CE3-E15BC89679F9"},"AnimationType":"object3D","is_imported":false,"isEnabled":true},{"@class":"AnimationScript","id":{"uuid":"A9497710-9F07-4BD2-A3A1-1F48D840389E"},"name":"Particles","enableOnAwake":false,"OwnerLink":{"@class":"BindingLink","targetId":{"uuid":"7B431B4D-F6C4-44B2-A80D-92422D6E746E"},"targetRelativeAddress":{"@class":"NodeRelativeAddressBase","index":0,"name":"particles 2","subaddress":{"@class":"NodeRelativeAddressBase","index":1,"name":"P2","subaddress":{"@class":"NodeRelativeAddressBase","index":0,"name":"Particles"}}}},"animation":{"uuid":"AB47840E-1A0C-47C4-B20B-A49ACF470F81"},"AnimationType":"object3D","is_imported":false,"isEnabled":true},{"@class":"AnimationScript","id":{"uuid":"1D77F118-C001-4890-9280-140230860F08"},"name":"P3","enableOnAwake":false,"OwnerLink":{"@class":"BindingLink","targetId":{"uuid":"1C34191B-976D-4CB3-9F27-981E1E2F5B67"},"targetRelativeAddress":{"@class":"NodeRelativeAddressBase","index":0,"name":"particles 2","subaddress":{"@class":"NodeRelativeAddressBase","index":2,"name":"P3"}}},"animation":{"uuid":"2C841036-9656-4FD1-B765-898D6B0A61A1"},"AnimationType":"object3D","is_imported":false,"isEnabled":true},{"@class":"AnimationScript","id":{"uuid":"610CE5AE-E12B-4445-A65C-21FD0537CA04"},"name":"Particles","enableOnAwake":false,"OwnerLink":{"@class":"BindingLink","targetId":{"uuid":"3E04E931-E27A-4A3F-BB74-BCBD98CBB0B7"},"targetRelativeAddress":{"@class":"NodeRelativeAddressBase","index":0,"name":"particles 2","subaddress":{"@class":"NodeRelativeAddressBase","index":2,"name":"P3","subaddress":{"@class":"NodeRelativeAddressBase","index":0,"name":"Particles"}}}},"animation":{"uuid":"F9CEF109-ACCC-437D-B89D-4BE0E43F6AA4"},"AnimationType":"object3D","is_imported":false,"isEnabled":true},{"@class":"AnimationScript","id":{"uuid":"0D240A28-AB93-403C-AD06-8AD4B893BA9B"},"name":"P4","enableOnAwake":false,"OwnerLink":{"@class":"BindingLink","targetId":{"uuid":"FF504D5C-7497-4CA7-97D1-8A42F8BF4CCB"},"targetRelativeAddress":{"@class":"NodeRelativeAddressBase","index":0,"name":"particles 2","subaddress":{"@class":"NodeRelativeAddressBase","index":3,"name":"P4"}}},"animation":{"uuid":"6D9419A3-3867-429B-8D95-59A511862D4E"},"AnimationType":"object3D","is_imported":false,"isEnabled":true},{"@class":"AnimationScript","id":{"uuid":"8311BED4-EE42-4029-9515-204E87D9967E"},"name":"Particles","enableOnAwake":false,"OwnerLink":{"@class":"BindingLink","targetId":{"uuid":"CDE82386-28F2-442C-845C-2DF3E3999C50"},"targetRelativeAddress":{"@class":"NodeRelativeAddressBase","index":0,"name":"particles 2","subaddress":{"@class":"NodeRelativeAddressBase","index":3,"name":"P4","subaddress":{"@class":"NodeRelativeAddressBase","index":0,"name":"Particles"}}}},"animation":{"uuid":"B56DCE3B-EB26-4D7E-8571-1FB8633371FA"},"AnimationType":"object3D","is_imported":false,"isEnabled":true},{"@class":"AnimationScript","id":{"uuid":"5FF2B994-E4DC-44FC-AD8A-61F73275975C"},"name":"P5","enableOnAwake":false,"OwnerLink":{"@class":"BindingLink","targetId":{"uuid":"2DD3323D-DBB2-44E6-8CB1-A600D599CB2B"},"targetRelativeAddress":{"@class":"NodeRelativeAddressBase","index":0,"name":"particles 2","subaddress":{"@class":"NodeRelativeAddressBase","index":4,"name":"P5"}}},"animation":{"uuid":"1198772A-4D11-4472-9D8E-817791813587"},"AnimationType":"object3D","is_imported":false,"isEnabled":true},{"@class":"AnimationScript","id":{"uuid":"4D4A3783-E0AF-4C59-B0B5-BFF8D20EF27A"},"name":"Particles","enableOnAwake":false,"OwnerLink":{"@class":"BindingLink","targetId":{"uuid":"33277256-15A8-4B56-8656-46472076D99F"},"targetRelativeAddress":{"@class":"NodeRelativeAddressBase","index":0,"name":"particles 2","subaddress":{"@class":"NodeRelativeAddressBase","index":4,"name":"P5","subaddress":{"@class":"NodeRelativeAddressBase","index":0,"name":"Particles"}}}},"animation":{"uuid":"DA17D0C8-EB9D-4345-90CD-C2C9797F595C"},"AnimationType":"object3D","is_imported":false,"isEnabled":true},{"@class":"AnimationScript","id":{"uuid":"0F60C86C-932E-4010-9ECD-6CA60AE149B2"},"name":"P6","enableOnAwake":false,"OwnerLink":{"@class":"BindingLink","targetId":{"uuid":"1B6A2945-B786-40C7-B25D-9CA49BFE1E48"},"targetRelativeAddress":{"@class":"NodeRelativeAddressBase","index":0,"name":"particles 2","subaddress":{"@class":"NodeRelativeAddressBase","index":5,"name":"P6"}}},"animation":{"uuid":"C9061853-6D57-44B0-9617-13ED1D1C9DB8"},"AnimationType":"object3D","is_imported":false,"isEnabled":true},{"@class":"AnimationScript","id":{"uuid":"C9BA78D6-A13B-4DD5-8988-8C004DC41589"},"name":"Particles","enableOnAwake":false,"OwnerLink":{"@class":"BindingLink","targetId":{"uuid":"EC468984-23D7-4BF2-A7BD-8F6C458E472C"},"targetRelativeAddress":{"@class":"NodeRelativeAddressBase","index":0,"name":"particles 2","subaddress":{"@class":"NodeRelativeAddressBase","index":5,"name":"P6","subaddress":{"@class":"NodeRelativeAddressBase","index":0,"name":"Particles"}}}},"animation":{"uuid":"62BED37F-266F-475E-8CF0-090DF3A25FBC"},"AnimationType":"object3D","is_imported":false,"isEnabled":true},{"@class":"AnimationScript","id":{"uuid":"FA2F3239-B881-4AFF-8ABE-59EADD49B217"},"name":"P7","enableOnAwake":false,"OwnerLink":{"@class":"BindingLink","targetId":{"uuid":"91D83B1C-CA91-4E51-87F5-9DA69CE3DC48"},"targetRelativeAddress":{"@class":"NodeRelativeAddressBase","index":0,"name":"particles 2","subaddress":{"@class":"NodeRelativeAddressBase","index":6,"name":"P7"}}},"animation":{"uuid":"4F6FC319-4618-4A6F-B6E1-EED1FA527F39"},"AnimationType":"object3D","is_imported":false,"isEnabled":true},{"@class":"AnimationScript","id":{"uuid":"8D32C2C7-8593-4B61-8319-10FD4D9D7386"},"name":"Particles","enableOnAwake":false,"OwnerLink":{"@class":"BindingLink","targetId":{"uuid":"6D2BF578-0263-41CE-A848-F25E15966C13"},"targetRelativeAddress":{"@class":"NodeRelativeAddressBase","index":0,"name":"particles 2","subaddress":{"@class":"NodeRelativeAddressBase","index":6,"name":"P7","subaddress":{"@class":"NodeRelativeAddressBase","index":0,"name":"Particles"}}}},"animation":{"uuid":"EAA0C92B-C82D-4DC0-B22A-CD3807E5A741"},"AnimationType":"object3D","is_imported":false,"isEnabled":true},{"@class":"AnimationScript","id":{"uuid":"142E9029-D6AA-4566-B8F2-0784B50F3BF7"},"name":"P8C","enableOnAwake":false,"OwnerLink":{"@class":"BindingLink","targetId":{"uuid":"EF5922C3-93A3-4728-987C-997C3C7D70CB"},"targetRelativeAddress":{"@class":"NodeRelativeAddressBase","index":0,"name":"particles 2","subaddress":{"@class":"NodeRelativeAddressBase","index":7,"name":"P8C"}}},"animation":{"uuid":"1D158FA6-C3D7-478E-86C1-B826DE6F631D"},"AnimationType":"object3D","is_imported":false,"isEnabled":true},{"@class":"AnimationScript","id":{"uuid":"FE002439-03BA-4F5D-BE55-54107CB38EE4"},"name":"Particles","enableOnAwake":false,"OwnerLink":{"@class":"BindingLink","targetId":{"uuid":"C2DC8545-2C34-40B3-B087-342D123C6FB2"},"targetRelativeAddress":{"@class":"NodeRelativeAddressBase","index":0,"name":"particles 2","subaddress":{"@class":"NodeRelativeAddressBase","index":7,"name":"P8C","subaddress":{"@class":"NodeRelativeAddressBase","index":0,"name":"Particles"}}}},"animation":{"uuid":"8304FDEA-7C3E-498E-B120-03E8A3FC85AE"},"AnimationType":"object3D","is_imported":false,"isEnabled":true},{"@class":"AnimationScript","id":{"uuid":"2DFDB827-DEA2-42E9-8E71-2C9CB603AF0E"},"name":"P8C 2","enableOnAwake":false,"OwnerLink":{"@class":"BindingLink","targetId":{"uuid":"B77B6896-277E-458A-9CC9-E582AC3A605A"},"targetRelativeAddress":{"@class":"NodeRelativeAddressBase","index":0,"name":"particles 2","subaddress":{"@class":"NodeRelativeAddressBase","index":8,"name":"P8C 2"}}},"animation":{"uuid":"85639DF1-83E7-4451-9EEB-16DC8FF0E4C4"},"AnimationType":"object3D","is_imported":false,"isEnabled":true},{"@class":"AnimationScript","id":{"uuid":"C6482F96-9250-4DF7-9DE0-2DB0145E693A"},"name":"Particles","enableOnAwake":false,"OwnerLink":{"@class":"BindingLink","targetId":{"uuid":"CA6AC8FD-AF2E-4AD6-A1AF-4C0C57A209FB"},"targetRelativeAddress":{"@class":"NodeRelativeAddressBase","index":0,"name":"particles 2","subaddress":{"@class":"NodeRelativeAddressBase","index":8,"name":"P8C 2","subaddress":{"@class":"NodeRelativeAddressBase","index":0,"name":"Particles"}}}},"animation":{"uuid":"75E62A0B-5328-4D37-8677-CABE02EA90A6"},"AnimationType":"object3D","is_imported":false,"isEnabled":true}]},"triggers":[{"@class":"AnimationTrigger","id":{"uuid":"3A10AEE4-9D1B-45FA-8C5D-72CEBC61536E"},"ownerScriptId":{"uuid":"692F3C1C-141F-4D48-B1D5-F650B0434EBC"},"logicOperation":0,"resultType":0,"isInverted":false,"event":2,"bindingLink":{"@class":"BindingLink","targetId":{"uuid":"155EDC78-CB81-496C-8AD5-8196B809C071"}}},{"@class":"AnimationTrigger","id":{"uuid":"7F423E18-1699-4B16-8070-E94400DBA42E"},"ownerScriptId":{"uuid":"692F3C1C-141F-4D48-B1D5-F650B0434EBC"},"logicOperation":0,"resultType":0,"isInverted":false,"event":1,"bindingLink":{"@class":"BindingLink","targetId":{"uuid":"23169C40-FAF7-4A16-A392-E4EF988F56F3"}}}]}