{"@class":"TimeLineScript","id":{"uuid":"73429CC7-B054-40CE-AA91-3B9F993BDC66"},"name":"Scene_01 Animation 1","enableOnAwake":false,"loop":false,"jumpToFirstFrameAtEnd":false,"speed":1.0,"weight":1.0,"loopStartTime":0,"loopDuration":0,"is_imported":false,"type":"user","scripts":{"@class":"StdListRuntimeScript","list":[{"@class":"AnimationScript","id":{"uuid":"46CD7582-28D3-47BA-A26B-0E0D4E976E15"},"name":"Global_Respawn","enableOnAwake":false,"OwnerLink":{"@class":"BindingLink","targetId":{"uuid":"90BF75AB-FE3F-4951-A344-CF0B96540762"}},"animation":{"uuid":"286815A6-B9D5-4D1F-B794-2F456070DFBA"},"AnimationType":"object3D","is_imported":false,"isEnabled":true},{"@class":"AnimationScript","id":{"uuid":"01A20ECD-7338-40A7-B719-F2C289BE3C3F"},"name":"RiverCube2","enableOnAwake":false,"OwnerLink":{"@class":"BindingLink","targetId":{"uuid":"12C0498C-B85D-4884-A8C7-1AC152737ADE"}},"animation":{"uuid":"82F6FBF3-01B6-4370-8C64-CE5B42AC457A"},"AnimationType":"object3D","is_imported":false,"isEnabled":true},{"@class":"AnimationScript","id":{"uuid":"14123D90-8DE4-4F81-84F8-C15213B217FF"},"name":"RiverCube1","enableOnAwake":false,"OwnerLink":{"@class":"BindingLink","targetId":{"uuid":"BD8A136D-6410-49A2-B8C6-89896B81D52C"}},"animation":{"uuid":"F83A4883-861C-4A9E-83DA-CA9CF5C33709"},"AnimationType":"object3D","is_imported":false,"isEnabled":true},{"@class":"AnimationScript","id":{"uuid":"7F246044-C0B4-4088-8EDB-657C9DAEC83D"},"name":"Stone1","enableOnAwake":false,"OwnerLink":{"@class":"BindingLink","targetId":{"uuid":"D1CEFB0C-B96B-4133-8A8A-F872CC2BB467"}},"animation":{"uuid":"8BBF478D-AB17-4AF7-BD17-05AADF6029EC"},"AnimationType":"object3D","is_imported":false,"isEnabled":true},{"@class":"AnimationScript","id":{"uuid":"5163BC3F-87EA-457E-AC37-98BA12DB765B"},"name":"Stone2","enableOnAwake":false,"OwnerLink":{"@class":"BindingLink","targetId":{"uuid":"922F27C6-1E58-4143-8A00-F9EE0F598B04"}},"animation":{"uuid":"36A4CD87-1294-4F44-8C73-9DBEF0645B15"},"AnimationType":"object3D","is_imported":false,"isEnabled":true},{"@class":"AnimationScript","id":{"uuid":"1EDD7738-916C-41DA-BA80-5C030C43FDFB"},"name":"Stone3","enableOnAwake":false,"OwnerLink":{"@class":"BindingLink","targetId":{"uuid":"C5225D18-58B6-4AF3-AEDA-67493B95B454"}},"animation":{"uuid":"BD3F8B8F-3B33-411E-AD25-EFEEE629F669"},"AnimationType":"object3D","is_imported":false,"isEnabled":true}]},"triggers":[{"@class":"CollisionTrigger","id":{"uuid":"9B229746-0597-4C1E-BC5D-7D29E79E7147"},"ownerScriptId":{"uuid":"73429CC7-B054-40CE-AA91-3B9F993BDC66"},"logicOperation":0,"resultType":0,"isInverted":false,"eventType":"in","targetBindingLink":{"@class":"BindingLink","targetId":{"uuid":"B2170EB5-1DCB-4BCB-B239-768061E6F0CE"}},"zoneBindingLink":{"@class":"BindingLink","targetId":{"uuid":"C6ACBF67-0D4F-463D-83BD-D9B13CB8A56B"}},"allowed":false}]}