{"@class":"TimeLineScript","id":{"uuid":"74FF2736-1339-459F-A863-6A9462C29AA9"},"name":"Animation","enableOnAwake":false,"loop":true,"jumpToFirstFrameAtEnd":false,"speed":1.0,"weight":1.0,"loopStartTime":0,"loopDuration":0,"is_imported":false,"type":"user","scripts":{"@class":"StdListRuntimeScript","list":[{"@class":"AnimationScript","id":{"uuid":"CE710ECB-9FD9-43A1-BB7A-2B4D413D7787"},"name":"Cylinder.004","enableOnAwake":false,"OwnerLink":{"@class":"BindingLink","targetId":{"uuid":"3B17D7CB-E202-4942-B16A-DC9F4F3127FA"},"targetRelativeAddress":{"@class":"NodeRelativeAddressBase","index":8,"name":"P8C 2"}},"animation":{"uuid":"38437BCE-6B14-4723-8AFF-DB5D5FE34F32"},"AnimationType":"object3D","is_imported":false,"isEnabled":true}]},"triggers":[{"@class":"AnimationTrigger","id":{"uuid":"73D8D76A-CE67-4DF7-B1F2-FB18E949F758"},"ownerScriptId":{"uuid":"74FF2736-1339-459F-A863-6A9462C29AA9"},"logicOperation":0,"resultType":0,"isInverted":false,"event":1,"bindingLink":{"@class":"BindingLink","targetId":{"uuid":"F737CE88-E5E1-48A1-BD7F-1F74F0C7973F"}}}]}