{"@class":"TimeLineScript","id":{"uuid":"76B68F6A-7283-4509-B1D4-AD8482369119"},"name":"Animation","enableOnAwake":false,"loop":false,"jumpToFirstFrameAtEnd":false,"speed":1.0,"weight":1.0,"loopStartTime":0,"loopDuration":0,"is_imported":false,"type":"user","scripts":{"@class":"StdListRuntimeScript","list":[{"@class":"AnimationScript","id":{"uuid":"FE5D6D61-AFBA-4A79-B252-A373229CE5A7"},"name":"Cylinder.004","enableOnAwake":false,"OwnerLink":{"@class":"BindingLink","targetId":{"uuid":"3A25AE8D-E3EF-4837-9CD2-8C06103849C3"},"targetRelativeAddress":{"@class":"NodeRelativeAddressBase","index":4,"name":"Rain_droplets4","subaddress":{"@class":"NodeRelativeAddressBase","index":1,"name":"P1"}}},"animation":{"uuid":"34620001-E6B3-433B-94D0-D3C9BE1DD463"},"AnimationType":"object3D","is_imported":false,"isEnabled":true},{"@class":"AnimationScript","id":{"uuid":"A3CA2DA4-A977-4E56-AE58-476DC967D8CE"},"name":"Cylinder.004","enableOnAwake":false,"OwnerLink":{"@class":"BindingLink","targetId":{"uuid":"B8D51E41-E662-41BA-945B-58AFAAB4492F"}},"animation":{"uuid":"2C56264B-F14F-4032-836B-F294182AC35F"},"AnimationType":"object3D","is_imported":false,"isEnabled":true},{"@class":"AnimationScript","id":{"uuid":"D3C1EACB-F8A4-4512-A80F-BFD50A37DAB8"},"name":"Cylinder.004","enableOnAwake":false,"OwnerLink":{"@class":"BindingLink","targetId":{"uuid":"BCCF45E0-B7D9-41F5-AB26-F681E9BAE6AE"}},"animation":{"uuid":"3C6838FD-228B-41A1-A905-D0F8CBEA6FB8"},"AnimationType":"object3D","is_imported":false,"isEnabled":true},{"@class":"AnimationScript","id":{"uuid":"9ABE495D-190F-4537-8218-6B07FF6A1B70"},"name":"Cylinder.004","enableOnAwake":false,"OwnerLink":{"@class":"BindingLink","targetId":{"uuid":"B2B53660-BCC8-4F3C-A222-FC45C299F078"},"targetRelativeAddress":{"@class":"NodeRelativeAddressBase","index":4,"name":"Rain_droplets4","subaddress":{"@class":"NodeRelativeAddressBase","index":4,"name":"P4"}}},"animation":{"uuid":"DFE9CDE3-B8C6-4D3A-BEDE-97CB45DE8A90"},"AnimationType":"object3D","is_imported":false,"isEnabled":true}]},"triggers":[{"@class":"AnimationTrigger","id":{"uuid":"249F8AA0-94F6-4A6A-B9AF-52C63C72738F"},"ownerScriptId":{"uuid":"76B68F6A-7283-4509-B1D4-AD8482369119"},"logicOperation":0,"resultType":0,"isInverted":false,"event":1,"bindingLink":{"@class":"BindingLink","targetId":{"uuid":"D418AC97-79CD-483F-8B19-3A407A458E4B"}}}]}