{"@class":"TimeLineScript","id":{"uuid":"FD5071E8-D922-47E0-ADB1-792A51504918"},"name":"Animation","enableOnAwake":false,"loop":true,"jumpToFirstFrameAtEnd":false,"speed":1.0,"weight":1.0,"loopStartTime":0,"loopDuration":0,"is_imported":false,"type":"user","scripts":{"@class":"StdListRuntimeScript","list":[{"@class":"AnimationScript","id":{"uuid":"2E8E92F8-3998-420D-ADEB-B50942621F53"},"name":"Rain","enableOnAwake":false,"OwnerLink":{"@class":"BindingLink","targetId":{"uuid":"E7A5EE07-2DAC-41F1-A59F-A5E8D7F7CD1D"},"targetRelativeAddress":{"@class":"NodeRelativeAddressBase","index":5,"name":"Rain"}},"animation":{"uuid":"E4B29285-7FC1-4CFB-A9FC-70C38E372628"},"AnimationType":"object3D","is_imported":false,"isEnabled":true}]},"triggers":[{"@class":"StartTrigger","id":{"uuid":"BCF8FE0F-DCAD-4F8D-983C-A0F48B240C95"},"ownerScriptId":{"uuid":"FD5071E8-D922-47E0-ADB1-792A51504918"},"logicOperation":0,"resultType":0,"isInverted":false}]}